pysxml.py
pysxml-1.0.1.dist-info/LICENSE
pysxml-1.0.1.dist-info/METADATA
pysxml-1.0.1.dist-info/WHEEL
pysxml-1.0.1.dist-info/top_level.txt
pysxml-1.0.1.dist-info/RECORD
