Metadata-Version: 2.1
Name: pysxml
Version: 1.0.1
Summary: Generate XML and HTML using an SXML-like syntax
Home-page: https://codeberg.org/antero/pysxml
Author: Antero
License: BSD
Platform: UNKNOWN
License-File: LICENSE
